{
  "matchId": 2784569,
  "homeName": "莱切",
  "awayName": "那不勒斯",
  "events": [
    {
      "time": "26'",
      "kind": "AWAY",
      "process": "Regular",
      "type": "yellowCard",
      "player": {
        "id": 150893,
        "name": "奥利维拉"
      }
    },
    {
      "time": "",
      "kind": "OTHER",
      "process": "HalfTime",
      "type": "matchProcess",
      "score": {
        "home": 0,
        "away": 0
      }
    },
    {
      "time": "46'",
      "kind": "HOME",
      "process": "Regular",
      "type": "substitution",
      "playerOn": {
        "id": 156891,
        "name": "莫伦特"
      },
      "playerOff": {
        "id": 175979,
        "name": "皮亚罗迪"
      }
    },
    {
      "time": "48'",
      "kind": "AWAY",
      "process": "Regular",
      "type": "substitution",
      "playerOn": {
        "id": 147622,
        "name": "D·内雷斯"
      },
      "playerOff": {
        "id": 161083,
        "name": "诺亚"
      }
    },
    {
      "time": "54'",
      "kind": "HOME",
      "process": "Regular"
    },
    {
      "time": "56'",
      "kind": "HOME",
      "process": "Regular"
    },
    {
      "time": "61'",
      "kind": "AWAY",
      "process": "Regular",
      "type": "substitution",
      "playerOn": {
        "id": 201304,
        "name": "R.霍伊伦德"
      },
      "playerOff": {
        "id": 217235,
        "name": "L·卢卡"
      }
    },
    {
      "time": "61'",
      "kind": "AWAY",
      "process": "Regular",
      "type": "substitution",
      "playerOn": {
        "id": 153040,
        "name": "麦克托米奈"
      },
      "playerOff": {
        "id": 116026,
        "name": "M·波利塔诺"
      }
    },
    {
      "time": "61'",
      "kind": "AWAY",
      "process": "Regular",
      "type": "substitution",
      "playerOn": {
        "id": 77802,
        "name": "斯皮纳佐拉"
      },
      "playerOff": {
        "id": 150893,
        "name": "奥利维拉"
      }
    },
    {
      "time": "62'",
      "kind": "HOME",
      "process": "Regular",
      "type": "yellowCard",
      "player": {
        "id": 154096,
        "name": "拉曼达尼"
      }
    },
    {
      "time": "65'",
      "kind": "HOME",
      "process": "Regular",
      "type": "substitution",
      "playerOn": {
        "id": 174748,
        "name": "乔瑟林"
      },
      "playerOff": {
        "id": 177143,
        "name": "邦达"
      }
    },
    {
      "time": "69'",
      "kind": "AWAY",
      "process": "Regular",
      "type": "goal",
      "player": {
        "id": 135853,
        "name": "安古伊萨"
      },
      "assist": {
        "id": 147622,
        "name": "D·内雷斯"
      },
      "score": {
        "home": 0,
        "away": 1
      }
    },
    {
      "time": "70'",
      "kind": "HOME",
      "process": "Regular",
      "type": "substitution",
      "playerOn": {
        "id": 190877,
        "name": "斯图利奇"
      },
      "playerOff": {
        "id": 244237,
        "name": "F·卡马尔达"
      }
    },
    {
      "time": "77'",
      "kind": "HOME",
      "process": "Regular",
      "type": "substitution",
      "playerOn": {
        "id": 150824,
        "name": "马拉赫"
      },
      "playerOff": {
        "id": 138914,
        "name": "库利巴利"
      }
    },
    {
      "time": "77'",
      "kind": "HOME",
      "process": "Regular",
      "type": "substitution",
      "playerOn": {
        "id": 183517,
        "name": "巴尔塔扎尔·皮耶雷"
      },
      "playerOff": {
        "id": 228462,
        "name": "M·贝里沙"
      }
    },
    {
      "time": "85'",
      "kind": "AWAY",
      "process": "Regular",
      "type": "substitution",
      "playerOn": {
        "id": 177755,
        "name": "米盖尔.奥尔特加"
      },
      "playerOff": {
        "id": 152324,
        "name": "埃尔马斯"
      }
    },
    {
      "time": "88'",
      "kind": "HOME",
      "process": "Regular",
      "type": "yellowCard",
      "player": {
        "id": 174748,
        "name": "乔瑟林"
      }
    },
    {
      "time": "",
      "kind": "OTHER",
      "process": "FullTime",
      "type": "matchProcess",
      "score": {
        "home": 0,
        "away": 1
      }
    }
  ],
  "cornerEvents": {
    "homeId": 158,
    "guestId": 1419,
    "home": 3,
    "homeHalf": 0,
    "guest": 5,
    "guestHalf": 2,
    "detail": [
      {
        "min": "13",
        "ifHome": false
      },
      {
        "min": "16",
        "ifHome": false
      },
      {
        "min": "47",
        "ifHome": true
      },
      {
        "min": "51",
        "ifHome": true
      },
      {
        "min": "66",
        "ifHome": false
      },
      {
        "min": "68",
        "ifHome": false
      },
      {
        "min": "68",
        "ifHome": false
      },
      {
        "min": "72",
        "ifHome": true
      },
      {
        "min": "90",
        "ifHome": false
      }
    ]
  }
}