{
  "matchId": 2852224,
  "homeName": "布赖代合作",
  "awayName": "阿科多",
  "events": [
    {
      "time": "6'",
      "kind": "AWAY",
      "process": "Regular",
      "type": "yellowCard",
      "player": {
        "id": 213372,
        "name": "鲁巴伊"
      }
    },
    {
      "time": "18'",
      "kind": "AWAY",
      "process": "Regular"
    },
    {
      "time": "20'",
      "kind": "AWAY",
      "process": "Regular"
    },
    {
      "time": "31'",
      "kind": "AWAY",
      "process": "Regular",
      "type": "yellowCard",
      "player": {
        "id": 241433,
        "name": "纳伊夫·阿塞里"
      }
    },
    {
      "time": "34'",
      "kind": "HOME",
      "process": "Regular"
    },
    {
      "time": "35'",
      "kind": "HOME",
      "process": "Regular",
      "type": "yellowCard",
      "player": {
        "id": 297375,
        "name": "森贝内"
      }
    },
    {
      "time": "41'",
      "kind": "HOME",
      "process": "Regular",
      "type": "substitution",
      "playerOn": {
        "id": 239717,
        "name": "M·阿莱利"
      },
      "playerOff": {
        "id": 297375,
        "name": "森贝内"
      }
    },
    {
      "time": "",
      "kind": "OTHER",
      "process": "HalfTime",
      "type": "matchProcess",
      "score": {
        "home": 0,
        "away": 0
      }
    },
    {
      "time": "57'",
      "kind": "AWAY",
      "process": "Regular",
      "type": "substitution",
      "playerOn": {
        "id": 172251,
        "name": "佩德罗萨"
      },
      "playerOff": {
        "id": 241433,
        "name": "纳伊夫·阿塞里"
      }
    },
    {
      "time": "58'",
      "kind": "HOME",
      "process": "Regular",
      "type": "goal",
      "player": {
        "id": 220498,
        "name": "M·卡塔尼"
      },
      "assist": {
        "id": 0,
        "name": ""
      },
      "score": {
        "home": 1,
        "away": 0
      }
    },
    {
      "time": "78'",
      "kind": "HOME",
      "process": "Regular",
      "type": "substitution",
      "playerOn": {
        "id": 239649,
        "name": "阿吉尔"
      },
      "playerOff": {
        "id": 214413,
        "name": "克里斯托珀·赞布拉诺"
      }
    },
    {
      "time": "79'",
      "kind": "AWAY",
      "process": "Regular",
      "type": "substitution",
      "playerOn": {
        "id": 291509,
        "name": "A.阿尔萨利姆"
      },
      "playerOff": {
        "id": 288392,
        "name": "G·哈萨维"
      }
    },
    {
      "time": "80'",
      "kind": "AWAY",
      "process": "Regular",
      "type": "substitution",
      "playerOn": {
        "id": 179230,
        "name": "萨利赫·阿巴斯"
      },
      "playerOff": {
        "id": 98187,
        "name": "尼古恩"
      }
    },
    {
      "time": "83'",
      "kind": "HOME",
      "process": "Regular",
      "type": "yellowCard",
      "player": {
        "id": 121631,
        "name": "罗格.马丁内斯"
      }
    },
    {
      "time": "85'",
      "kind": "HOME",
      "process": "Regular",
      "type": "substitution",
      "playerOn": {
        "id": 239674,
        "name": "A·哈瓦萨维"
      },
      "playerOff": {
        "id": 220498,
        "name": "M·卡塔尼"
      }
    },
    {
      "time": "86'",
      "kind": "AWAY",
      "process": "Regular",
      "type": "yellowCard",
      "player": {
        "id": 352276,
        "name": "阿希"
      }
    },
    {
      "time": "86'",
      "kind": "HOME",
      "process": "Regular",
      "type": "substitution",
      "playerOn": {
        "id": 288057,
        "name": "A·哈尔比"
      },
      "playerOff": {
        "id": 239554,
        "name": "A·巴胡赛因"
      }
    },
    {
      "time": "",
      "kind": "OTHER",
      "process": "FullTime",
      "type": "matchProcess",
      "score": {
        "home": 1,
        "away": 0
      }
    }
  ],
  "cornerEvents": {
    "homeId": 7087,
    "guestId": 7096,
    "home": 12,
    "homeHalf": 4,
    "guest": 3,
    "guestHalf": 2,
    "detail": [
      {
        "min": "2",
        "ifHome": true
      },
      {
        "min": "5",
        "ifHome": true
      },
      {
        "min": "14",
        "ifHome": false
      },
      {
        "min": "16",
        "ifHome": false
      },
      {
        "min": "27",
        "ifHome": true
      },
      {
        "min": "42",
        "ifHome": true
      },
      {
        "min": "47",
        "ifHome": true
      },
      {
        "min": "50",
        "ifHome": true
      },
      {
        "min": "61",
        "ifHome": true
      },
      {
        "min": "62",
        "ifHome": true
      },
      {
        "min": "62",
        "ifHome": true
      },
      {
        "min": "68",
        "ifHome": true
      },
      {
        "min": "72",
        "ifHome": false
      },
      {
        "min": "73",
        "ifHome": true
      },
      {
        "min": "90",
        "ifHome": true
      }
    ]
  }
}