{
  "matchId": 2784707,
  "homeName": "那不勒斯",
  "awayName": "佛罗伦萨",
  "events": [
    {
      "time": "11'",
      "kind": "HOME",
      "process": "Regular",
      "type": "goal",
      "player": {
        "id": 221324,
        "name": "安东尼奥·维加拉"
      },
      "assist": {
        "id": 124679,
        "name": "梅雷特"
      },
      "score": {
        "home": 1,
        "away": 0
      }
    },
    {
      "time": "30'",
      "kind": "HOME",
      "process": "Regular",
      "type": "substitution",
      "playerOn": {
        "id": 150893,
        "name": "奥利维拉"
      },
      "playerOff": {
        "id": 161537,
        "name": "G·迪洛伦佐"
      }
    },
    {
      "time": "44'",
      "kind": "AWAY",
      "process": "Regular",
      "type": "yellowCard",
      "player": {
        "id": 219548,
        "name": "G·法比安"
      }
    },
    {
      "time": "",
      "kind": "OTHER",
      "process": "HalfTime",
      "type": "matchProcess",
      "score": {
        "home": 1,
        "away": 0
      }
    },
    {
      "time": "46'",
      "kind": "AWAY",
      "process": "Regular",
      "type": "substitution",
      "playerOn": {
        "id": 124688,
        "name": "曼德拉格拉"
      },
      "playerOff": {
        "id": 219548,
        "name": "G·法比安"
      }
    },
    {
      "time": "49'",
      "kind": "HOME",
      "process": "Regular",
      "type": "goal",
      "player": {
        "id": 177755,
        "name": "米盖尔.奥尔特加"
      },
      "assist": {
        "id": 221324,
        "name": "安东尼奥·维加拉"
      },
      "score": {
        "home": 2,
        "away": 0
      }
    },
    {
      "time": "54'",
      "kind": "HOME",
      "process": "Regular",
      "type": "yellowCard",
      "player": {
        "id": 151000,
        "name": "布翁吉奥诺"
      }
    },
    {
      "time": "57'",
      "kind": "AWAY",
      "process": "Regular",
      "type": "goal",
      "player": {
        "id": 161185,
        "name": "索罗门"
      },
      "assist": {
        "id": 0,
        "name": ""
      },
      "score": {
        "home": 2,
        "away": 1
      }
    },
    {
      "time": "70'",
      "kind": "AWAY",
      "process": "Regular",
      "type": "substitution",
      "playerOn": {
        "id": 203717,
        "name": "帕里西"
      },
      "playerOff": {
        "id": 161185,
        "name": "索罗门"
      }
    },
    {
      "time": "70'",
      "kind": "AWAY",
      "process": "Regular",
      "type": "substitution",
      "playerOn": {
        "id": 164759,
        "name": "拉涅利"
      },
      "playerOff": {
        "id": 119362,
        "name": "戈森斯"
      }
    },
    {
      "time": "70'",
      "kind": "AWAY",
      "process": "Regular",
      "type": "substitution",
      "playerOn": {
        "id": 148979,
        "name": "莫伊斯.基恩"
      },
      "playerOff": {
        "id": 166734,
        "name": "布雷西亚尼"
      }
    },
    {
      "time": "79'",
      "kind": "AWAY",
      "process": "Regular",
      "type": "substitution",
      "playerOn": {
        "id": 221592,
        "name": "法兹尼"
      },
      "playerOff": {
        "id": 135673,
        "name": "古德蒙德松"
      }
    },
    {
      "time": "84'",
      "kind": "HOME",
      "process": "Regular",
      "type": "substitution",
      "playerOn": {
        "id": 172762,
        "name": "吉奥瓦尼"
      },
      "playerOff": {
        "id": 221324,
        "name": "安东尼奥·维加拉"
      }
    },
    {
      "time": "90+1'",
      "kind": "HOME",
      "process": "Regular",
      "type": "substitution",
      "playerOn": {
        "id": 66664,
        "name": "卢卡库"
      },
      "playerOff": {
        "id": 201304,
        "name": "R.霍伊伦德"
      }
    },
    {
      "time": "",
      "kind": "OTHER",
      "process": "FullTime",
      "type": "matchProcess",
      "score": {
        "home": 2,
        "away": 1
      }
    }
  ],
  "cornerEvents": {
    "homeId": 1419,
    "guestId": 176,
    "home": 4,
    "homeHalf": 2,
    "guest": 4,
    "guestHalf": 3,
    "detail": [
      {
        "min": "9",
        "ifHome": true
      },
      {
        "min": "20",
        "ifHome": true
      },
      {
        "min": "26",
        "ifHome": false
      },
      {
        "min": "32",
        "ifHome": false
      },
      {
        "min": "33",
        "ifHome": false
      },
      {
        "min": "67",
        "ifHome": true
      },
      {
        "min": "77",
        "ifHome": false
      },
      {
        "min": "90",
        "ifHome": true
      }
    ]
  }
}