{
  "matchId": 2921435,
  "homeName": "阿森纳",
  "awayName": "维冈竞技",
  "events": [
    {
      "time": "11'",
      "kind": "HOME",
      "process": "Regular",
      "type": "goal",
      "player": {
        "id": 180561,
        "name": "N·马杜埃凯"
      },
      "assist": {
        "id": 150512,
        "name": "E·埃泽"
      },
      "score": {
        "home": 1,
        "away": 0
      }
    },
    {
      "time": "18'",
      "kind": "HOME",
      "process": "Regular",
      "type": "goal",
      "player": {
        "id": 168935,
        "name": "马丁内利"
      },
      "assist": {
        "id": 150512,
        "name": "E·埃泽"
      },
      "score": {
        "home": 2,
        "away": 0
      }
    },
    {
      "time": "23'",
      "kind": "HOME",
      "process": "Regular"
    },
    {
      "time": "27'",
      "kind": "HOME",
      "process": "Regular",
      "type": "goal",
      "player": {
        "id": 131976,
        "name": "热苏斯"
      },
      "assist": {
        "id": 103074,
        "name": "诺尔加德"
      },
      "score": {
        "home": 4,
        "away": 0
      }
    },
    {
      "time": "30'",
      "kind": "AWAY",
      "process": "Regular",
      "type": "substitution",
      "playerOn": {
        "id": 202013,
        "name": "M.史密斯"
      },
      "playerOff": {
        "id": 79536,
        "name": "亨特"
      }
    },
    {
      "time": "",
      "kind": "OTHER",
      "process": "HalfTime",
      "type": "matchProcess",
      "score": {
        "home": 4,
        "away": 0
      }
    },
    {
      "time": "46'",
      "kind": "HOME",
      "process": "Regular",
      "type": "substitution",
      "playerOn": {
        "id": 151881,
        "name": "约克雷斯"
      },
      "playerOff": {
        "id": 171322,
        "name": "萨卡"
      }
    },
    {
      "time": "61'",
      "kind": "HOME",
      "process": "Regular",
      "type": "substitution",
      "playerOn": {
        "id": 317666,
        "name": "M.萨蒙"
      },
      "playerOff": {
        "id": 167450,
        "name": "萨利巴"
      }
    },
    {
      "time": "62'",
      "kind": "HOME",
      "process": "Regular",
      "type": "substitution",
      "playerOn": {
        "id": 102096,
        "name": "特罗萨德"
      },
      "playerOff": {
        "id": 180561,
        "name": "N·马杜埃凯"
      }
    },
    {
      "time": "63'",
      "kind": "AWAY",
      "process": "Regular",
      "type": "substitution",
      "playerOn": {
        "id": 190910,
        "name": "卡斯特洛"
      },
      "playerOff": {
        "id": 135498,
        "name": "J.泰勒"
      }
    },
    {
      "time": "69'",
      "kind": "HOME",
      "process": "Regular",
      "type": "yellowCard",
      "player": {
        "id": 249070,
        "name": "斯凯利"
      }
    },
    {
      "time": "73'",
      "kind": "AWAY",
      "process": "Regular",
      "type": "yellowCard",
      "player": {
        "id": 146219,
        "name": "O.莫克森"
      }
    },
    {
      "time": "77'",
      "kind": "AWAY",
      "process": "Regular",
      "type": "substitution",
      "playerOn": {
        "id": 293015,
        "name": "贝托尼"
      },
      "playerOff": {
        "id": 181551,
        "name": "拉斐尔"
      }
    },
    {
      "time": "77'",
      "kind": "AWAY",
      "process": "Regular",
      "type": "substitution",
      "playerOn": {
        "id": 156908,
        "name": "塞塞尼翁"
      },
      "playerOff": {
        "id": 125426,
        "name": "杰森克尔"
      }
    },
    {
      "time": "78'",
      "kind": "AWAY",
      "process": "Regular",
      "type": "substitution",
      "playerOn": {
        "id": 183433,
        "name": "J.洪波"
      },
      "playerOff": {
        "id": 146219,
        "name": "O.莫克森"
      }
    },
    {
      "time": "79'",
      "kind": "HOME",
      "process": "Regular",
      "type": "substitution",
      "playerOn": {
        "id": 174795,
        "name": "祖比门迪"
      },
      "playerOff": {
        "id": 145438,
        "name": "怀特"
      }
    },
    {
      "time": "82'",
      "kind": "HOME",
      "process": "Regular",
      "type": "yellowCard",
      "player": {
        "id": 103074,
        "name": "诺尔加德"
      }
    },
    {
      "time": "83'",
      "kind": "AWAY",
      "process": "Regular",
      "type": "yellowCard",
      "player": {
        "id": 150582,
        "name": "阿米森"
      }
    },
    {
      "time": "87'",
      "kind": "HOME",
      "process": "Regular",
      "type": "substitution",
      "playerOn": {
        "id": 240820,
        "name": "塞特福德"
      },
      "playerOff": {
        "id": 99273,
        "name": "凯帕"
      }
    },
    {
      "time": "",
      "kind": "OTHER",
      "process": "FullTime",
      "type": "matchProcess",
      "score": {
        "home": 4,
        "away": 0
      }
    }
  ],
  "cornerEvents": {
    "homeId": 19,
    "guestId": 61,
    "home": 5,
    "homeHalf": 3,
    "guest": 0,
    "guestHalf": 0,
    "detail": [
      {
        "min": "8",
        "ifHome": true
      },
      {
        "min": "25",
        "ifHome": true
      },
      {
        "min": "39",
        "ifHome": true
      },
      {
        "min": "50",
        "ifHome": true
      },
      {
        "min": "69",
        "ifHome": true
      }
    ]
  }
}