{
  "homeFormation": "4-2-3-1",
  "guestFormation": "4-3-3",
  "homeStarting": [
    {
      "id": 130371,
      "number": "1",
      "name": "布特兹",
      "captainType": 0,
      "injuryReson": ""
    },
    {
      "id": 126182,
      "number": "31",
      "name": "维约达",
      "captainType": 0,
      "injuryReson": ""
    },
    {
      "id": 135376,
      "number": "34",
      "name": "卡洛斯",
      "captainType": 0,
      "injuryReson": ""
    },
    {
      "id": 259692,
      "number": "14",
      "name": "J·拉蒙",
      "captainType": 0,
      "injuryReson": ""
    },
    {
      "id": 110817,
      "number": "18",
      "name": "莫雷诺",
      "captainType": 0,
      "injuryReson": ""
    },
    {
      "id": 221344,
      "number": "23",
      "name": "佩罗内",
      "captainType": 0,
      "injuryReson": ""
    },
    {
      "id": 167077,
      "number": "6",
      "name": "卡格雷",
      "captainType": 0,
      "injuryReson": ""
    },
    {
      "id": 229090,
      "number": "42",
      "name": "阿达伊",
      "captainType": 0,
      "injuryReson": ""
    },
    {
      "id": 223514,
      "number": "10",
      "name": "N·帕兹",
      "captainType": 0,
      "injuryReson": ""
    },
    {
      "id": 266769,
      "number": "17",
      "name": "罗德里格斯",
      "captainType": 0,
      "injuryReson": ""
    },
    {
      "id": 161064,
      "number": "11",
      "name": "多维卡斯",
      "captainType": 0,
      "injuryReson": ""
    }
  ],
  "guestStarting": [
    {
      "id": 155114,
      "number": "49",
      "name": "穆里奇",
      "captainType": 0,
      "injuryReson": ""
    },
    {
      "id": 159859,
      "number": "6",
      "name": "S.瓦路基维斯",
      "captainType": 0,
      "injuryReson": ""
    },
    {
      "id": 168214,
      "number": "21",
      "name": "艾泽斯",
      "captainType": 0,
      "injuryReson": ""
    },
    {
      "id": 211203,
      "number": "80",
      "name": "穆哈雷莫维奇",
      "captainType": 0,
      "injuryReson": ""
    },
    {
      "id": 184092,
      "number": "3",
      "name": "乔希·多伊格",
      "captainType": 0,
      "injuryReson": ""
    },
    {
      "id": 218358,
      "number": "90",
      "name": "I·科內",
      "captainType": 0,
      "injuryReson": ""
    },
    {
      "id": 163538,
      "number": "42",
      "name": "托斯特维特",
      "captainType": 0,
      "injuryReson": ""
    },
    {
      "id": 62545,
      "number": "18",
      "name": "马蒂奇",
      "captainType": 0,
      "injuryReson": ""
    },
    {
      "id": 103731,
      "number": "10",
      "name": "贝拉尔迪",
      "captainType": 0,
      "injuryReson": ""
    },
    {
      "id": 145017,
      "number": "99",
      "name": "皮纳蒙蒂",
      "captainType": 0,
      "injuryReson": ""
    },
    {
      "id": 164800,
      "number": "45",
      "name": "劳伦特",
      "captainType": 0,
      "injuryReson": ""
    }
  ],
  "homeSubs": [
    {
      "id": 151227,
      "number": "27",
      "name": "波施",
      "captainType": 0,
      "injuryReson": ""
    },
    {
      "id": 180469,
      "number": "77",
      "name": "贝尔梅特",
      "captainType": 0,
      "injuryReson": ""
    },
    {
      "id": 200759,
      "number": "44",
      "name": "N·卡夫里纳",
      "captainType": 0,
      "injuryReson": ""
    },
    {
      "id": 203268,
      "number": "20",
      "name": "M.巴图里纳",
      "captainType": 0,
      "injuryReson": ""
    },
    {
      "id": 177905,
      "number": "33",
      "name": "达库尼亚",
      "captainType": 1,
      "injuryReson": ""
    },
    {
      "id": 102485,
      "number": "2",
      "name": "肯普夫",
      "captainType": 0,
      "injuryReson": ""
    },
    {
      "id": 27916,
      "number": "22",
      "name": "维格里托",
      "captainType": 0,
      "injuryReson": ""
    },
    {
      "id": 111158,
      "number": "99",
      "name": "塞里",
      "captainType": 0,
      "injuryReson": ""
    },
    {
      "id": 232761,
      "number": "3",
      "name": "瓦莱·戈麦斯",
      "captainType": 0,
      "injuryReson": ""
    },
    {
      "id": 79259,
      "number": "7",
      "name": "莫拉塔",
      "captainType": 0,
      "injuryReson": ""
    },
    {
      "id": 167337,
      "number": "19",
      "name": "尼古拉斯库恩",
      "captainType": 0,
      "injuryReson": ""
    }
  ],
  "guestSubs": [
    {
      "id": 219788,
      "number": "7",
      "name": "沃尔帕托",
      "captainType": 0,
      "injuryReson": ""
    },
    {
      "id": 177874,
      "number": "25",
      "name": "库利巴利",
      "captainType": 0,
      "injuryReson": ""
    },
    {
      "id": 193064,
      "number": "20",
      "name": "费德拉",
      "captainType": 0,
      "injuryReson": ""
    },
    {
      "id": 157173,
      "number": "5",
      "name": "法利德",
      "captainType": 0,
      "injuryReson": ""
    },
    {
      "id": 141259,
      "number": "12",
      "name": "萨塔利诺",
      "captainType": 0,
      "injuryReson": ""
    },
    {
      "id": 261663,
      "number": "16",
      "name": "G·扎基",
      "captainType": 0,
      "injuryReson": ""
    },
    {
      "id": 204727,
      "number": "44",
      "name": "伊恩诺尼",
      "captainType": 0,
      "injuryReson": ""
    },
    {
      "id": 140148,
      "number": "77",
      "name": "皮耶里尼",
      "captainType": 0,
      "injuryReson": ""
    },
    {
      "id": 228704,
      "number": "9",
      "name": "切迪拉",
      "captainType": 0,
      "injuryReson": ""
    },
    {
      "id": 179606,
      "number": "26",
      "name": "奥登塔尔",
      "captainType": 0,
      "injuryReson": ""
    },
    {
      "id": 291672,
      "number": "33",
      "name": "弗兰盖拉",
      "captainType": 0,
      "injuryReson": ""
    },
    {
      "id": 286281,
      "number": "31",
      "name": "马基奥尼",
      "captainType": 0,
      "injuryReson": ""
    },
    {
      "id": 189723,
      "number": "24",
      "name": "莫罗",
      "captainType": 0,
      "injuryReson": ""
    }
  ],
  "homeInjury": [
    {
      "id": 205357,
      "number": "28",
      "name": "伊万·斯莫里奇",
      "captainType": 0,
      "injuryReson": "黄牌累计停赛"
    },
    {
      "id": 82014,
      "number": "8",
      "name": "罗伯托",
      "captainType": 0,
      "injuryReson": "腘绳肌拉伤"
    },
    {
      "id": 240678,
      "number": "38",
      "name": "D.迪奥",
      "captainType": 0,
      "injuryReson": "腘绳肌损伤"
    },
    {
      "id": 109341,
      "number": "5",
      "name": "格尔达尼加",
      "captainType": 0,
      "injuryReson": "跟腱问题"
    },
    {
      "id": 153095,
      "number": "4",
      "name": "多塞纳",
      "captainType": 0,
      "injuryReson": "伤病"
    }
  ],
  "guestInjury": [
    {
      "id": 180484,
      "number": "40",
      "name": "万科斯",
      "captainType": 0,
      "injuryReson": "未知的损伤"
    },
    {
      "id": 182227,
      "number": "13",
      "name": "图拉蒂",
      "captainType": 0,
      "injuryReson": "手腕受伤"
    },
    {
      "id": 203478,
      "number": "11",
      "name": "波洛卡",
      "captainType": 0,
      "injuryReson": "膝关节问题"
    },
    {
      "id": 221581,
      "number": "17",
      "name": "叶弗森",
      "captainType": 0,
      "injuryReson": "未知的损伤"
    },
    {
      "id": 120252,
      "number": "19",
      "name": "罗马尼亚",
      "captainType": 0,
      "injuryReson": "肌肉问题"
    },
    {
      "id": 221580,
      "number": "15",
      "name": "皮埃拉格诺洛",
      "captainType": 0,
      "injuryReson": "十字韧带损伤"
    },
    {
      "id": 179606,
      "number": "26",
      "name": "奥登塔尔",
      "captainType": 0,
      "injuryReson": "冷流感"
    },
    {
      "id": 231984,
      "number": "35",
      "name": "利帕尼",
      "captainType": 0,
      "injuryReson": "冷流感"
    },
    {
      "id": 191901,
      "number": "14",
      "name": "拉努斯·斯凯勒鲁普",
      "captainType": 0,
      "injuryReson": "受伤"
    }
  ],
  "matchId": 2784604,
  "homeName": "科莫",
  "awayName": "萨索洛"
}